mkv_this/__init__.py
mkv_this/__main__.py
mkv_this/functions.py
mkv_this/mkv_this.py
mkv_this-0.2.5.dist-info/LICENSE
mkv_this-0.2.5.dist-info/METADATA
mkv_this-0.2.5.dist-info/WHEEL
mkv_this-0.2.5.dist-info/entry_points.txt
mkv_this-0.2.5.dist-info/test.py
mkv_this-0.2.5.dist-info/top_level.txt
mkv_this-0.2.5.dist-info/RECORD
