Metadata-Version: 2.1
Name: mkv-this
Version: 0.2.5
Summary: cli wrapper for markovify: take a text file, directory, pdf or url, markovify, save the results.
Home-page: https://git.disroot.org/mousebot/mkv-this
Author: mousebot
Author-email: martianhiatus@riseup.net
License: AGPLv3
Platform: UNKNOWN
Requires-Dist: markovify
Requires-Dist: argparse
Requires-Dist: html2text
Requires-Dist: requests
